Topsis_Deepankar_Varma_102003431/Deepankar_Varma_102003431.py
Topsis_Deepankar_Varma_102003431-0.19.dist-info/METADATA
Topsis_Deepankar_Varma_102003431-0.19.dist-info/WHEEL
Topsis_Deepankar_Varma_102003431-0.19.dist-info/entry_points.txt
Topsis_Deepankar_Varma_102003431-0.19.dist-info/top_level.txt
Topsis_Deepankar_Varma_102003431-0.19.dist-info/RECORD
