Metadata-Version: 2.1
Name: Topsis-Deepankar-Varma-102003431
Version: 0.19
Summary: This is a topsis package of Deepankar Varma version 0.19
Author: Deepankar Varma
Author-email: satiwkdprhrit@gmail.com
Requires-Dist: pandas
